gnomehat/__init__.py
gnomehat/file_input.py
gnomehat/local_ip.py
gnomehat/server_config.py
gnomehat/sysinfo.py
gnomehat/console/__init__.py
gnomehat/console/args.py
gnomehat/console/run.py
gnomehat/console/wizard.py
gnomehat/server/__init__.py
gnomehat/server/datasource.py
gnomehat/server/webapi.py
gnomehat/static/css/main.css
gnomehat/static/css/normalize.css
gnomehat/static/css/skeleton.css
gnomehat/static/images/default.png
gnomehat/static/images/favicon.png
gnomehat/static/images/gnome_black.png
gnomehat/static/images/gnome_grey.png
gnomehat/static/images/gnome_white.png
gnomehat/static/images/screenshot_CPPN.jpg
gnomehat/static/images/screenshot_Mask_RCNN.jpg
gnomehat/static/images/screenshot_Rainbow.jpg
gnomehat/static/images/screenshot_char_rnn.jpg
gnomehat/static/images/screenshot_classifier_cifar10.jpg
gnomehat/static/images/screenshot_progressive_growing_of_gans.jpg
gnomehat/static/images/screenshot_sc2microbattle.jpg
gnomehat/static/images/screenshot_variational_autoencoder.jpg
gnomehat/static/js/filter.js
gnomehat/static/js/sorttable.js
gnomehat/static/js/ws-repl.js
gnomehat/templates/demos.html
gnomehat/templates/experiment.html
gnomehat/templates/experiment_header.html
gnomehat/templates/experiment_listing.html
gnomehat/templates/index.html
gnomehat/templates/list_namespaces.html
gnomehat/templates/listing.html
gnomehat/templates/main_header.html
gnomehat/templates/metrics.html
gnomehat/templates/metrics_listing.html
gnomehat/templates/namespace_table.html
gnomehat-0.7.17.data/scripts/gnomehat
gnomehat-0.7.17.data/scripts/gnomehat_cleanup
gnomehat-0.7.17.data/scripts/gnomehat_doctor
gnomehat-0.7.17.data/scripts/gnomehat_install_standalone_python
gnomehat-0.7.17.data/scripts/gnomehat_server
gnomehat-0.7.17.data/scripts/gnomehat_websocket
gnomehat-0.7.17.data/scripts/gnomehat_worker
gnomehat-0.7.17.dist-info/LICENSE.txt
gnomehat-0.7.17.dist-info/METADATA
gnomehat-0.7.17.dist-info/WHEEL
gnomehat-0.7.17.dist-info/top_level.txt
gnomehat-0.7.17.dist-info/RECORD
