Metadata-Version: 2.1
Name: gnomehat
Version: 0.7.17
Summary: GnomeHat: easy experiment control
Home-page: UNKNOWN
Author: Larry Neal
Author-email: nealla@lwneal.com
License: UNKNOWN
Platform: UNKNOWN
Requires-Python: >3
Requires-Dist: requests
Requires-Dist: flask
Requires-Dist: pytz
Requires-Dist: websockets
Requires-Dist: docopt
